{
    "keep": {
        "days": true,
        "amount": 14
    },
    "auditLog": "log\\.9e0e70c869af7dde0e9b3bd00cfb023c441e1c3d-audit.json",
    "files": [
        {
            "date": 1542767754632,
            "name": "log\\application-2018-11-20-20.log",
            "hash": "a56c4e243d1b59936fd9e8230e2f7bc2"
        },
        {
            "date": 1542769777425,
            "name": "log\\application-2018-11-20-21.log",
            "hash": "dcfb51a1b7d13bd1c654258865555186"
        },
        {
            "date": 1542773056499,
            "name": "log\\application-2018-11-20-22.log",
            "hash": "4cbcdf35c3620b3d9b2b8a3d8e79300b"
        },
        {
            "date": 1542851170754,
            "name": "log\\application-2018-11-21-19.log",
            "hash": "4a6b598716fe82f704d3e5be281e24a0"
        },
        {
            "date": 1542855311874,
            "name": "log\\application-2018-11-21-20.log",
            "hash": "dcae6d798a7b6bd7254cfa02123806b2"
        },
        {
            "date": 1542855604719,
            "name": "log\\application-2018-11-21-21.log",
            "hash": "ba80a8ee029034e8ca826cb4d51ae807"
        },
        {
            "date": 1542859203033,
            "name": "log\\application-2018-11-21-22.log",
            "hash": "a76a496b8178658cb6e4a001a09bfbdd"
        },
        {
            "date": 1543511518127,
            "name": "log\\application-2018-11-29-11.log",
            "hash": "c01f3d44367d52bb006204d8c80f6146"
        },
        {
            "date": 1543514667953,
            "name": "log\\application-2018-11-29-12.log",
            "hash": "ef4d3e872af81a3b682af66b155e3201"
        },
        {
            "date": 1543524846898,
            "name": "log\\application-2018-11-29-14.log",
            "hash": "86ff918f7f34a23a8083241fb724baa9"
        },
        {
            "date": 1543543819515,
            "name": "log\\application-2018-11-29-20.log",
            "hash": "1791945f7518fc24da6d8f9fff4c778b"
        },
        {
            "date": 1543547350443,
            "name": "log\\application-2018-11-29-21.log",
            "hash": "0123d1b10929a94bc1cf24f5e672e59f"
        },
        {
            "date": 1543714717168,
            "name": "log\\application-2018-12-01-19.log",
            "hash": "f6384a20bc3e63180d44ab3ebd4420ed"
        },
        {
            "date": 1543878890508,
            "name": "log\\application-2018-12-03-17.log",
            "hash": "89915b08b081756fc5d739907d177d60"
        },
        {
            "date": 1543882709795,
            "name": "log\\application-2018-12-03-18.log",
            "hash": "617e3a6f330e12169408885004fab614"
        }
    ]
}